crawl/__init__.py
crawl/screen_shot.py
universal_utils-0.0.1.dist-info/METADATA
universal_utils-0.0.1.dist-info/RECORD
universal_utils-0.0.1.dist-info/WHEEL
universal_utils-0.0.1.dist-info/top_level.txt
