Metadata-Version: 2.1
Name: universal-utils
Version: 0.0.1
Summary: python utils
Home-page: https://github.com/Tsotsi/python_utils
Author: tsotsi
Author-email: tsotsi@tsotsi.cn
License: UNKNOWN
Platform: UNKNOWN
Classifier: Programming Language :: Python :: 3
Classifier: License :: OSI Approved :: MIT License
Classifier: Operating System :: OS Independent
